telemetry_tempest_plugin/__init__.py
telemetry_tempest_plugin/config.py
telemetry_tempest_plugin/exceptions.py
telemetry_tempest_plugin/plugin.py
telemetry_tempest_plugin/aodh/__init__.py
telemetry_tempest_plugin/aodh/api/__init__.py
telemetry_tempest_plugin/aodh/api/base.py
telemetry_tempest_plugin/aodh/api/test_alarming_api.py
telemetry_tempest_plugin/aodh/api/test_alarming_api_negative.py
telemetry_tempest_plugin/aodh/api/admin/__init__.py
telemetry_tempest_plugin/aodh/api/admin/test_alarming_api_admin.py
telemetry_tempest_plugin/aodh/api/gnocchi/__init__.py
telemetry_tempest_plugin/aodh/api/gnocchi/test_alarming_api.py
telemetry_tempest_plugin/aodh/api/gnocchi/test_alarming_api_negative.py
telemetry_tempest_plugin/aodh/api/prometheus/__init__.py
telemetry_tempest_plugin/aodh/api/sql/__init__.py
telemetry_tempest_plugin/aodh/api/sql/test_alarming_api.py
telemetry_tempest_plugin/aodh/service/__init__.py
telemetry_tempest_plugin/aodh/service/client.py
telemetry_tempest_plugin/scenario/__init__.py
telemetry_tempest_plugin/scenario/test_gnocchi.py
telemetry_tempest_plugin/scenario/test_telemetry_integration.py
telemetry_tempest_plugin/scenario/test_telemetry_integration_prometheus.py
telemetry_tempest_plugin/scenario/utils.py
telemetry_tempest_plugin/scenario/gnocchi_gabbits/live.yaml
telemetry_tempest_plugin/scenario/gnocchi_gabbits/search-resource.yaml
telemetry_tempest_plugin/scenario/telemetry_integration_gabbits/aodh-gnocchi-threshold-alarm.yaml
telemetry_tempest_plugin/scenario/telemetry_integration_gabbits/autoscaling.yaml
telemetry_tempest_plugin/scenario/telemetry_integration_gabbits/create_stack.json
telemetry_tempest_plugin/scenario/telemetry_integration_prometheus_gabbits/autoscaling.yaml
telemetry_tempest_plugin/scenario/telemetry_integration_prometheus_gabbits/ceilometer-sg-core-integration.yaml
telemetry_tempest_plugin/scenario/telemetry_integration_prometheus_gabbits/create_stack.json
telemetry_tempest_plugin-2.8.0.dist-info/licenses/AUTHORS
telemetry_tempest_plugin-2.8.0.dist-info/licenses/LICENSE
telemetry_tempest_plugin-2.8.0.dist-info/METADATA
telemetry_tempest_plugin-2.8.0.dist-info/WHEEL
telemetry_tempest_plugin-2.8.0.dist-info/entry_points.txt
telemetry_tempest_plugin-2.8.0.dist-info/pbr.json
telemetry_tempest_plugin-2.8.0.dist-info/top_level.txt
telemetry_tempest_plugin-2.8.0.dist-info/RECORD
